Workbook

Sheet Données
A1: Tableau des charges fixes
B3: par mois | C3: par an
A4: loyer | B4: 1000 | C4: =B4*12 -> 12000
A5: cuisine | B5: =C5/12 -> 250 | C5: 3000
A6: factures edf eau | B6: 200 | C6: =B6*12 -> 2400
A7: entretien | B7: 100 | C7: =B7*12 -> 1200
A8: publicité | B8: =C8/12 -> 66.666667 | C8: 800
A9: prime assurance | B9: =C9/12 -> 100 | C9: 1200
A10: emprunt bancaire | B10: 250 | C10: =B10*12 -> 3000
A11: personnel | B11: 2730 | C11: =B11*12 -> 32760
A12: TOTAL | B12: =SUM(B4:B11) -> 4696.6667 | C12: =SUM(C4:C11) -> 56360
A14: Tableau du prix des ventes
B16: prix / vente
A17: menu 1 | B17: 15
A18: menu 2 | B18: 25
A19: menu 3 | B19: 35
A20: soft | B20: 3
A21: alcool | B21: 6
A23: Tableau des matières premières
B25: coût / vente
A26: menu 1 | B26: 10
A27: menu 2 | B27: 15
A28: menu 3 | B28: 20
A29: soft | B29: 1
A30: alcool | B30: 2
A32: taxe menu | B32: 0.1 | D32: taxe menu (aide État) | E32: 0.05
A33: taxe boisson | B33: 0.2 | D33: taxe boisson (aide État) | E33: 0.05
A36: Tableau répartition des ventes sur 2016
A38: Type de vente | B38: Jan | C38: Fév | D38: Mars | E38: Avr | F38: Mai | G38: Juin | H38: Juil | I38: Août | J38: Sept | K38: Oct | L38: Nov | M38: Déc
A39: Menu 1 | B39: 130 | C39: 70 | D39: 250 | E39: 220 | F39: 70 | G39: 150 | H39: 100 | I39: 240 | J39: 60 | K39: 70 | L39: 100 | M39: 130
A40: Menu 2 | B40: 90 | C40: 90 | D40: 210 | E40: 80 | F40: 160 | G40: 140 | H40: 200 | I40: 150 | J40: 90 | K40: 170 | L40: 230 | M40: 60
A41: Menu 3 | B41: 80 | C41: 130 | D41: 180 | E41: 90 | F41: 210 | G41: 250 | H41: 70 | I41: 140 | J41: 80 | K41: 60 | L41: 190 | M41: 130
A42: Soft | B42: 130 | C42: 250 | D42: 60 | E42: 190 | F42: 250 | G42: 130 | H42: 170 | I42: 110 | J42: 150 | K42: 60 | L42: 210 | M42: 60
A43: alcool | B43: 130 | C43: 180 | D43: 140 | E43: 240 | F43: 90 | G43: 180 | H43: 170 | I43: 90 | J43: 140 | K43: 220 | L43: 140 | M43: 190

Sheet Bilan 2016
B1: Jan | C1: Fév | D1: Mars | E1: Avr | F1: Mai | G1: Juin | H1: Juil | I1: Août | J1: Sept | K1: Oct | L1: Nov | M1: Déc | N1: TOTAL
A2: CA menu 1 | B2: =Données!B39*Données!$B$17 -> 1950 | C2: =Données!C39*Données!$B$17 -> 1050 | D2: =Données!D39*Données!$B$17 -> 3750 | E2: =Données!E39*Données!$B$17 -> 3300 | F2: =Données!F39*Données!$B$17 -> 1050 | G2: =Données!G39*Données!$B$17 -> 2250 | H2: =Données!H39*Données!$B$17 -> 1500 | I2: =Données!I39*Données!$B$17 -> 3600 | ... M2: =Données!M39*Données!$B$17 -> 1950 | N2: =SUM(B2:M2) -> 23850
A3: CA menu 2 | B3: =Données!B40*Données!$B$18 -> 2250 | C3: =Données!C40*Données!$B$18 -> 2250 | D3: =Données!D40*Données!$B$18 -> 5250 | E3: =Données!E40*Données!$B$18 -> 2000 | F3: =Données!F40*Données!$B$18 -> 4000 | G3: =Données!G40*Données!$B$18 -> 3500 | H3: =Données!H40*Données!$B$18 -> 5000 | I3: =Données!I40*Données!$B$18 -> 3750 | ... M3: =Données!M40*Données!$B$18 -> 1500 | N3: =SUM(B3:M3) -> 41750
A4: CA menu 3 | B4: =Données!B41*Données!$B$19 -> 2800 | C4: =Données!C41*Données!$B$19 -> 4550 | D4: =Données!D41*Données!$B$19 -> 6300 | E4: =Données!E41*Données!$B$19 -> 3150 | F4: =Données!F41*Données!$B$19 -> 7350 | G4: =Données!G41*Données!$B$19 -> 8750 | H4: =Données!H41*Données!$B$19 -> 2450 | I4: =Données!I41*Données!$B$19 -> 4900 | ... M4: =Données!M41*Données!$B$19 -> 4550 | N4: =SUM(B4:M4) -> 56350
A5: CA soft | B5: =Données!B42*Données!$B$20 -> 390 | C5: =Données!C42*Données!$B$20 -> 750 | D5: =Données!D42*Données!$B$20 -> 180 | E5: =Données!E42*Données!$B$20 -> 570 | F5: =Données!F42*Données!$B$20 -> 750 | G5: =Données!G42*Données!$B$20 -> 390 | H5: =Données!H42*Données!$B$20 -> 510 | I5: =Données!I42*Données!$B$20 -> 330 | ... M5: =Données!M42*Données!$B$20 -> 180 | N5: =SUM(B5:M5) -> 5310
A6: CA alcool | B6: =Données!B43*Données!$B$21 -> 780 | C6: =Données!C43*Données!$B$21 -> 1080 | D6: =Données!D43*Données!$B$21 -> 840 | E6: =Données!E43*Données!$B$21 -> 1440 | F6: =Données!F43*Données!$B$21 -> 540 | G6: =Données!G43*Données!$B$21 -> 1080 | H6: =Données!H43*Données!$B$21 -> 1020 | I6: =Données!I43*Données!$B$21 -> 540 | ... M6: =Données!M43*Données!$B$21 -> 1140 | N6: =SUM(B6:M6) -> 11460
A7: TOTAL CA | B7: =SUM(B2:B6) -> 8170 | C7: =SUM(C2:C6) -> 9680 | D7: =SUM(D2:D6) -> 16320 | E7: =SUM(E2:E6) -> 10460 | F7: =SUM(F2:F6) -> 13690 | G7: =SUM(G2:G6) -> 15970 | H7: =SUM(H2:H6) -> 10480 | I7: =SUM(I2:I6) -> 13120 | ... M7: =SUM(M2:M6) -> 9320 | N7: =SUM(B7:M7) -> 138720
A8: Charge fixe | B8: =Données!$B$12 -> 4696.6667 | C8: =Données!$B$12 -> 4696.6667 | D8: =Données!$B$12 -> 4696.6667 | E8: =Données!$B$12 -> 4696.6667 | F8: =Données!$B$12 -> 4696.6667 | G8: =Données!$B$12 -> 4696.6667 | H8: =Données!$B$12 -> 4696.6667 | I8: =Données!$B$12 -> 4696.6667 | ... M8: =Données!$B$12 -> 4696.6667 | N8: =SUM(B8:M8) -> 56360
A9: matière 1ère menu 1 | B9: =Données!B39*Données!$B$26 -> 1300 | C9: =Données!C39*Données!$B$26 -> 700 | D9: =Données!D39*Données!$B$26 -> 2500 | E9: =Données!E39*Données!$B$26 -> 2200 | F9: =Données!F39*Données!$B$26 -> 700 | G9: =Données!G39*Données!$B$26 -> 1500 | H9: =Données!H39*Données!$B$26 -> 1000 | I9: =Données!I39*Données!$B$26 -> 2400 | ... M9: =Données!M39*Données!$B$26 -> 1300 | N9: =SUM(B9:M9) -> 15900
A10: matière 1ère menu 2 | B10: =Données!B40*Données!$B$27 -> 1350 | C10: =Données!C40*Données!$B$27 -> 1350 | D10: =Données!D40*Données!$B$27 -> 3150 | E10: =Données!E40*Données!$B$27 -> 1200 | F10: =Données!F40*Données!$B$27 -> 2400 | G10: =Données!G40*Données!$B$27 -> 2100 | H10: =Données!H40*Données!$B$27 -> 3000 | I10: =Données!I40*Données!$B$27 -> 2250 | ... M10: =Données!M40*Données!$B$27 -> 900 | N10: =SUM(B10:M10) -> 25050
A11: matière 1ère menu 3 | B11: =Données!B41*Données!$B$28 -> 1600 | C11: =Données!C41*Données!$B$28 -> 2600 | D11: =Données!D41*Données!$B$28 -> 3600 | E11: =Données!E41*Données!$B$28 -> 1800 | F11: =Données!F41*Données!$B$28 -> 4200 | G11: =Données!G41*Données!$B$28 -> 5000 | H11: =Données!H41*Données!$B$28 -> 1400 | I11: =Données!I41*Données!$B$28 -> 2800 | ... M11: =Données!M41*Données!$B$28 -> 2600 | N11: =SUM(B11:M11) -> 32200
A12: matière 1ère soft | B12: =Données!B42*Données!$B$29 -> 130 | C12: =Données!C42*Données!$B$29 -> 250 | D12: =Données!D42*Données!$B$29 -> 60 | E12: =Données!E42*Données!$B$29 -> 190 | F12: =Données!F42*Données!$B$29 -> 250 | G12: =Données!G42*Données!$B$29 -> 130 | H12: =Données!H42*Données!$B$29 -> 170 | I12: =Données!I42*Données!$B$29 -> 110 | ... M12: =Données!M42*Données!$B$29 -> 60 | N12: =SUM(B12:M12) -> 1770
A13: matière 1ère alcool | B13: =Données!B43*Données!$B$30 -> 260 | C13: =Données!C43*Données!$B$30 -> 360 | D13: =Données!D43*Données!$B$30 -> 280 | E13: =Données!E43*Données!$B$30 -> 480 | F13: =Données!F43*Données!$B$30 -> 180 | G13: =Données!G43*Données!$B$30 -> 360 | H13: =Données!H43*Données!$B$30 -> 340 | I13: =Données!I43*Données!$B$30 -> 180 | ... M13: =Données!M43*Données!$B$30 -> 380 | N13: =SUM(B13:M13) -> 3820
A14: taxe menu | B14: =SUM(B2:B4)*Données!$B$32 -> 700 | C14: =SUM(C2:C4)*Données!$B$32 -> 785 | D14: =SUM(D2:D4)*Données!$B$32 -> 1530 | E14: =SUM(E2:E4)*Données!$B$32 -> 845 | F14: =SUM(F2:F4)*Données!$B$32 -> 1240 | G14: =SUM(G2:G4)*Données!$B$32 -> 1450 | H14: =SUM(H2:H4)*Données!$B$32 -> 895 | I14: =SUM(I2:I4)*Données!$B$32 -> 1225 | ... M14: =SUM(M2:M4)*Données!$B$32 -> 800 | N14: =SUM(B14:M14) -> 12195
A15: taxe boisson | B15: =SUM(B5:B6)*Données!$B$33 -> 234 | C15: =SUM(C5:C6)*Données!$B$33 -> 366 | D15: =SUM(D5:D6)*Données!$B$33 -> 204 | E15: =SUM(E5:E6)*Données!$B$33 -> 402 | F15: =SUM(F5:F6)*Données!$B$33 -> 258 | G15: =SUM(G5:G6)*Données!$B$33 -> 294 | H15: =SUM(H5:H6)*Données!$B$33 -> 306 | I15: =SUM(I5:I6)*Données!$B$33 -> 174 | ... M15: =SUM(M5:M6)*Données!$B$33 -> 264 | N15: =SUM(B15:M15) -> 3354
A16: charge variable | B16: =SUM(B9:B15) -> 5574 | C16: =SUM(C9:C15) -> 6411 | D16: =SUM(D9:D15) -> 11324 | E16: =SUM(E9:E15) -> 7117 | F16: =SUM(F9:F15) -> 9228 | G16: =SUM(G9:G15) -> 10834 | H16: =SUM(H9:H15) -> 7111 | I16: =SUM(I9:I15) -> 9139 | ... M16: =SUM(M9:M15) -> 6304 | N16: =SUM(B16:M16) -> 94289
A17: total coûts | B17: =B8+B16 -> 10270.667 | C17: =C8+C16 -> 11107.667 | D17: =D8+D16 -> 16020.667 | E17: =E8+E16 -> 11813.667 | F17: =F8+F16 -> 13924.667 | G17: =G8+G16 -> 15530.667 | H17: =H8+H16 -> 11807.667 | I17: =I8+I16 -> 13835.667 | ... M17: =M8+M16 -> 11000.667 | N17: =SUM(B17:M17) -> 150649
A18: Résultat | B18: =B7-B17 -> -2100.6667 | C18: =C7-C17 -> -1427.6667 | D18: =D7-D17 -> 299.33333 | E18: =E7-E17 -> -1353.6667 | F18: =F7-F17 -> -234.66667 | G18: =G7-G17 -> 439.33333 | H18: =H7-H17 -> -1327.6667 | I18: =I7-I17 -> -715.66667 | ... M18: =M7-M17 -> -1680.6667 | N18: =SUM(B18:M18) -> -11929

Sheet Simulation Aide État (5%)
B1: Jan | C1: Fév | D1: Mars | E1: Avr | F1: Mai | G1: Juin | H1: Juil | I1: Août | J1: Sept | K1: Oct | L1: Nov | M1: Déc | N1: TOTAL
A2: CA menu 1 | B2: =Données!B39*Données!$B$17 -> 1950 | C2: =Données!C39*Données!$B$17 -> 1050 | D2: =Données!D39*Données!$B$17 -> 3750 | E2: =Données!E39*Données!$B$17 -> 3300 | F2: =Données!F39*Données!$B$17 -> 1050 | G2: =Données!G39*Données!$B$17 -> 2250 | H2: =Données!H39*Données!$B$17 -> 1500 | I2: =Données!I39*Données!$B$17 -> 3600 | ... M2: =Données!M39*Données!$B$17 -> 1950 | N2: =SUM(B2:M2) -> 23850
A3: CA menu 2 | B3: =Données!B40*Données!$B$18 -> 2250 | C3: =Données!C40*Données!$B$18 -> 2250 | D3: =Données!D40*Données!$B$18 -> 5250 | E3: =Données!E40*Données!$B$18 -> 2000 | F3: =Données!F40*Données!$B$18 -> 4000 | G3: =Données!G40*Données!$B$18 -> 3500 | H3: =Données!H40*Données!$B$18 -> 5000 | I3: =Données!I40*Données!$B$18 -> 3750 | ... M3: =Données!M40*Données!$B$18 -> 1500 | N3: =SUM(B3:M3) -> 41750
A4: CA menu 3 | B4: =Données!B41*Données!$B$19 -> 2800 | C4: =Données!C41*Données!$B$19 -> 4550 | D4: =Données!D41*Données!$B$19 -> 6300 | E4: =Données!E41*Données!$B$19 -> 3150 | F4: =Données!F41*Données!$B$19 -> 7350 | G4: =Données!G41*Données!$B$19 -> 8750 | H4: =Données!H41*Données!$B$19 -> 2450 | I4: =Données!I41*Données!$B$19 -> 4900 | ... M4: =Données!M41*Données!$B$19 -> 4550 | N4: =SUM(B4:M4) -> 56350
A5: CA soft | B5: =Données!B42*Données!$B$20 -> 390 | C5: =Données!C42*Données!$B$20 -> 750 | D5: =Données!D42*Données!$B$20 -> 180 | E5: =Données!E42*Données!$B$20 -> 570 | F5: =Données!F42*Données!$B$20 -> 750 | G5: =Données!G42*Données!$B$20 -> 390 | H5: =Données!H42*Données!$B$20 -> 510 | I5: =Données!I42*Données!$B$20 -> 330 | ... M5: =Données!M42*Données!$B$20 -> 180 | N5: =SUM(B5:M5) -> 5310
A6: CA alcool | B6: =Données!B43*Données!$B$21 -> 780 | C6: =Données!C43*Données!$B$21 -> 1080 | D6: =Données!D43*Données!$B$21 -> 840 | E6: =Données!E43*Données!$B$21 -> 1440 | F6: =Données!F43*Données!$B$21 -> 540 | G6: =Données!G43*Données!$B$21 -> 1080 | H6: =Données!H43*Données!$B$21 -> 1020 | I6: =Données!I43*Données!$B$21 -> 540 | ... M6: =Données!M43*Données!$B$21 -> 1140 | N6: =SUM(B6:M6) -> 11460
A7: TOTAL CA | B7: =SUM(B2:B6) -> 8170 | C7: =SUM(C2:C6) -> 9680 | D7: =SUM(D2:D6) -> 16320 | E7: =SUM(E2:E6) -> 10460 | F7: =SUM(F2:F6) -> 13690 | G7: =SUM(G2:G6) -> 15970 | H7: =SUM(H2:H6) -> 10480 | I7: =SUM(I2:I6) -> 13120 | ... M7: =SUM(M2:M6) -> 9320 | N7: =SUM(B7:M7) -> 138720
A8: Charge fixe | B8: =Données!$B$12 -> 4696.6667 | C8: =Données!$B$12 -> 4696.6667 | D8: =Données!$B$12 -> 4696.6667 | E8: =Données!$B$12 -> 4696.6667 | F8: =Données!$B$12 -> 4696.6667 | G8: =Données!$B$12 -> 4696.6667 | H8: =Données!$B$12 -> 4696.6667 | I8: =Données!$B$12 -> 4696.6667 | ... M8: =Données!$B$12 -> 4696.6667 | N8: =SUM(B8:M8) -> 56360
A9: matière 1ère menu 1 | B9: =Données!B39*Données!$B$26 -> 1300 | C9: =Données!C39*Données!$B$26 -> 700 | D9: =Données!D39*Données!$B$26 -> 2500 | E9: =Données!E39*Données!$B$26 -> 2200 | F9: =Données!F39*Données!$B$26 -> 700 | G9: =Données!G39*Données!$B$26 -> 1500 | H9: =Données!H39*Données!$B$26 -> 1000 | I9: =Données!I39*Données!$B$26 -> 2400 | ... M9: =Données!M39*Données!$B$26 -> 1300 | N9: =SUM(B9:M9) -> 15900
A10: matière 1ère menu 2 | B10: =Données!B40*Données!$B$27 -> 1350 | C10: =Données!C40*Données!$B$27 -> 1350 | D10: =Données!D40*Données!$B$27 -> 3150 | E10: =Données!E40*Données!$B$27 -> 1200 | F10: =Données!F40*Données!$B$27 -> 2400 | G10: =Données!G40*Données!$B$27 -> 2100 | H10: =Données!H40*Données!$B$27 -> 3000 | I10: =Données!I40*Données!$B$27 -> 2250 | ... M10: =Données!M40*Données!$B$27 -> 900 | N10: =SUM(B10:M10) -> 25050
A11: matière 1ère menu 3 | B11: =Données!B41*Données!$B$28 -> 1600 | C11: =Données!C41*Données!$B$28 -> 2600 | D11: =Données!D41*Données!$B$28 -> 3600 | E11: =Données!E41*Données!$B$28 -> 1800 | F11: =Données!F41*Données!$B$28 -> 4200 | G11: =Données!G41*Données!$B$28 -> 5000 | H11: =Données!H41*Données!$B$28 -> 1400 | I11: =Données!I41*Données!$B$28 -> 2800 | ... M11: =Données!M41*Données!$B$28 -> 2600 | N11: =SUM(B11:M11) -> 32200
A12: matière 1ère soft | B12: =Données!B42*Données!$B$29 -> 130 | C12: =Données!C42*Données!$B$29 -> 250 | D12: =Données!D42*Données!$B$29 -> 60 | E12: =Données!E42*Données!$B$29 -> 190 | F12: =Données!F42*Données!$B$29 -> 250 | G12: =Données!G42*Données!$B$29 -> 130 | H12: =Données!H42*Données!$B$29 -> 170 | I12: =Données!I42*Données!$B$29 -> 110 | ... M12: =Données!M42*Données!$B$29 -> 60 | N12: =SUM(B12:M12) -> 1770
A13: matière 1ère alcool | B13: =Données!B43*Données!$B$30 -> 260 | C13: =Données!C43*Données!$B$30 -> 360 | D13: =Données!D43*Données!$B$30 -> 280 | E13: =Données!E43*Données!$B$30 -> 480 | F13: =Données!F43*Données!$B$30 -> 180 | G13: =Données!G43*Données!$B$30 -> 360 | H13: =Données!H43*Données!$B$30 -> 340 | I13: =Données!I43*Données!$B$30 -> 180 | ... M13: =Données!M43*Données!$B$30 -> 380 | N13: =SUM(B13:M13) -> 3820
A14: taxe menu | B14: =SUM(B2:B4)*Données!$E$32 -> 350 | C14: =SUM(C2:C4)*Données!$E$32 -> 392.5 | D14: =SUM(D2:D4)*Données!$E$32 -> 765 | E14: =SUM(E2:E4)*Données!$E$32 -> 422.5 | F14: =SUM(F2:F4)*Données!$E$32 -> 620 | G14: =SUM(G2:G4)*Données!$E$32 -> 725 | H14: =SUM(H2:H4)*Données!$E$32 -> 447.5 | I14: =SUM(I2:I4)*Données!$E$32 -> 612.5 | ... M14: =SUM(M2:M4)*Données!$E$32 -> 400 | N14: =SUM(B14:M14) -> 6097.5
A15: taxe boisson | B15: =SUM(B5:B6)*Données!$E$33 -> 58.5 | C15: =SUM(C5:C6)*Données!$E$33 -> 91.5 | D15: =SUM(D5:D6)*Données!$E$33 -> 51 | E15: =SUM(E5:E6)*Données!$E$33 -> 100.5 | F15: =SUM(F5:F6)*Données!$E$33 -> 64.5 | G15: =SUM(G5:G6)*Données!$E$33 -> 73.5 | H15: =SUM(H5:H6)*Données!$E$33 -> 76.5 | I15: =SUM(I5:I6)*Données!$E$33 -> 43.5 | ... M15: =SUM(M5:M6)*Données!$E$33 -> 66 | N15: =SUM(B15:M15) -> 838.5
A16: charge variable | B16: =SUM(B9:B15) -> 5048.5 | C16: =SUM(C9:C15) -> 5744 | D16: =SUM(D9:D15) -> 10406 | E16: =SUM(E9:E15) -> 6393 | F16: =SUM(F9:F15) -> 8414.5 | G16: =SUM(G9:G15) -> 9888.5 | H16: =SUM(H9:H15) -> 6434 | I16: =SUM(I9:I15) -> 8396 | ... M16: =SUM(M9:M15) -> 5706 | N16: =SUM(B16:M16) -> 85676
A17: total coûts | B17: =B8+B16 -> 9745.1667 | C17: =C8+C16 -> 10440.667 | D17: =D8+D16 -> 15102.667 | E17: =E8+E16 -> 11089.667 | F17: =F8+F16 -> 13111.167 | G17: =G8+G16 -> 14585.167 | H17: =H8+H16 -> 11130.667 | I17: =I8+I16 -> 13092.667 | ... M17: =M8+M16 -> 10402.667 | N17: =SUM(B17:M17) -> 142036
A18: Résultat | B18: =B7-B17 -> -1575.1667 | C18: =C7-C17 -> -760.66667 | D18: =D7-D17 -> 1217.3333 | E18: =E7-E17 -> -629.66667 | F18: =F7-F17 -> 578.83333 | G18: =G7-G17 -> 1384.8333 | H18: =H7-H17 -> -650.66667 | I18: =I7-I17 -> 27.333333 | ... M18: =M7-M17 -> -1082.6667 | N18: =SUM(B18:M18) -> -3316
